rt_client/__init__.py
rt_client/_version.py
rt_client/client.py
rt_client/exceptions.py
rt_client/common/utils.py
rt_client/shell/__init__.py
rt_client/tests/__init__.py
rt_client/tests/test_utils.py
rt_client/tests/test_v2_attachments.py
rt_client/tests/test_v2_client.py
rt_client/tests/test_v2_tickets.py
rt_client/v2/__init__.py
rt_client/v2/attachments.py
rt_client/v2/client.py
rt_client/v2/customfields.py
rt_client/v2/record_manager.py
rt_client/v2/tickets.py
rt_client/v2/transactions.py
rt_client-0.6.2.dist-info/licenses/LICENSE
rt_client-0.6.2.dist-info/METADATA
rt_client-0.6.2.dist-info/WHEEL
rt_client-0.6.2.dist-info/pbr.json
rt_client-0.6.2.dist-info/top_level.txt
rt_client-0.6.2.dist-info/RECORD
